pylint_pyspark/__init__.py
pylint_pyspark/author_checker.py
pylint_pyspark/case_import_checker.py
pylint_pyspark/chained_function_checker.py
pylint_pyspark/confluence_page_checker.py
pylint_pyspark/function_call_checker.py
pylint_pyspark/logic_op_complexity_checker.py
pylint_pyspark/module_display_checker.py
pylint_pyspark/module_print_checker.py
pylint_pyspark/module_show_checker.py
pylint_pyspark/pylint_utils.py
pylint_pyspark/select_alias_checker.py
pylint_pyspark/select_cast_checker.py
pylint_pyspark/statement_call_checker.py
pylint_pyspark-1.0.103.dist-info/LICENSE
pylint_pyspark-1.0.103.dist-info/METADATA
pylint_pyspark-1.0.103.dist-info/WHEEL
pylint_pyspark-1.0.103.dist-info/top_level.txt
pylint_pyspark-1.0.103.dist-info/RECORD
