Metadata-Version: 2.1
Name: pylint-pyspark
Version: 1.0.103
Summary: PySpark Style Guide
Home-page: https://github.com/AstrumU/pylint-pyspark
Author: Aman Ankit
Author-email: aman@astrumu.com
Classifier: Programming Language :: Python :: 3
Classifier: License :: OSI Approved :: MIT License
Classifier: Operating System :: OS Independent
License-File: LICENSE
Requires-Dist: pylint
